cfn_macro/__init__.py
cfn_macro/cfn_macro.py
cfn_macro-0.1.0.dist-info/AUTHORS.rst
cfn_macro-0.1.0.dist-info/METADATA
cfn_macro-0.1.0.dist-info/WHEEL
cfn_macro-0.1.0.dist-info/top_level.txt
cfn_macro-0.1.0.dist-info/RECORD
