Metadata-Version: 2.1
Name: cfn-macro
Version: 0.1.0
Summary: Core python package for cfnmacro library
Home-page: https://github.com/johnpreston/cfn_macro
Author: John Mille
Author-email: JohnPreston@users.noreply.github.com
License: UNKNOWN
Keywords: cfn_macro
Platform: UNKNOWN
Classifier: Development Status :: 2 - Pre-Alpha
Classifier: Intended Audience :: Developers
Classifier: Natural Language :: English
Classifier: Programming Language :: Python :: 3
Classifier: Programming Language :: Python :: 3.6
Classifier: Programming Language :: Python :: 3.7
